{"evaluationEntity":{"id":"5b3d2a39-f808-4348-bfa9-20ac3f98760c","dataResult":{},"analysedDataType":"none"},"validationEntity":{"analysedDataType":"auto","dataResult":{"createdDate":"2024-03-09T18:17:14Z"}},"activityEntities":["experimentCreated",[{"event":"experimentCreated","title":"Model Source Created","subtitle":"MyTabularClassifier 2","createdDate":"2024-03-09T18:17:14Z","id":"F1C2AA07-E028-40AA-8A80-9F0D0F1EE5C9"}]],"createdDate":"2024-03-09T18:17:14Z","version":"1.0","title":"MyTabularClassifier 2","snapshotRole":{"withoutSnapshots":0},"state":"uninitialized","contentDataResult":{"createdDate":"2024-03-09T18:17:14Z"},"trainingEntity":{"dataResult":{"createdDate":"2024-03-09T18:17:14Z"},"progress":[],"checkpointMetrics":{},"analysedDataType":"choose","snapshottableCheckpoints":{},"featureExtractionCheckpointMayBeAvailable":false},"evaluationContainerEntity":{"trainingEvaluationEntity":{"id":"182c2690-5c14-4402-aabf-67f0166cd852","createdDate":"2024-03-09T18:17:14Z","dataResult":{"createdDate":"2024-03-09T18:17:14Z"},"analysedDataType":"none"},"id":"f541b6c5-afbb-4930-8f04-c6e209d1cfe6","modifiedDate":"2024-03-09T18:17:27Z","validationEvaluationEntity":{"analysedDataType":"auto","dataResult":{"createdDate":"2024-03-09T18:17:14Z"},"createdDate":"2024-03-09T18:17:14Z","id":"b12ce055-0a59-4f93-bb7c-28cae0661373"},"testingEvaluationEntity":{"dataResult":{"createdDate":"2024-03-09T18:17:14Z"},"id":"87723a1e-bed9-4e85-9557-f6453a708bbc","analysedDataType":"none","createdDate":"2024-03-09T18:17:14Z"},"evaluationEntities":[],"createdDate":"2024-03-09T18:17:27Z","previewType":"tabularClassifier"},"settingEntity":{"seedType":"default","handActionClassifierAugmentations":[],"transferLearningEmbeddingType":"dynamic","taskType":"generalClassifier","styleTransferAlgorithmType":"image","harVideoAugmentations":0,"algorithmType":"maxEnt","handPoseClassifierAugmentations":[],"augmentations":[],"generalClassifierType":{"randomForestClassifier":{"minChildWeight":0.1,"maxDepth":6,"minLossReduction":0,"rowSubsample":0.8,"columnSubsample":0.8}},"featureNames":[]},"modifiedDate":"2024-03-09T18:17:27Z","evaluationState":"uninitialized","modelEntity":{"createdDate":"2024-03-09T18:17:14Z","title":"","id":"C2BE5795-F103-47F9-975B-4BAA015B7808","version":"1.0","modifiedDate":"2024-03-09T18:17:14Z","preferredFilename":"","experimentID":"39CD16D8-1F5A-4430-AA2F-F0CC8EE5D2F9"},"preferredFilename":"MyTabularClassifier 2","id":"39CD16D8-1F5A-4430-AA2F-F0CC8EE5D2F9"}